ava_shared_resources/__init__.py
ava_shared_resources/aws_utils.py
ava_shared_resources/collection_mapping_utils.py
ava_shared_resources/config_processing_utils.py
ava_shared_resources/configurations/__init__.py
ava_shared_resources/configurations/config.py
ava_shared_resources/configurations/gunicorn_conf.py
ava_shared_resources/configurations/gunicorn_config.py
ava_shared_resources/configurations/gunicorn_logging.cfg
ava_shared_resources/configurations/gunicorn_logging_debug.cfg
ava_shared_resources/configurations/mm_config.py
ava_shared_resources/constants.py
ava_shared_resources/data_io_utils.py
ava_shared_resources/data_processing_utils.py
ava_shared_resources/dynamodb_utils.py
ava_shared_resources/log_handler.py
ava_shared_resources/onnx_model_utils.py
ava_shared_resources/response_handler.py
ava_shared_resources/retry_handler.py
ava_shared_resources-0.0.40.dist-info/METADATA
ava_shared_resources-0.0.40.dist-info/WHEEL
ava_shared_resources-0.0.40.dist-info/RECORD
