Metadata-Version: 2.1
Name: ava-shared-resources
Version: 0.0.40
Summary: Pydantic classes
Home-page: https://bitbucket.wolterskluwer.io/projects/CCAI/repos/ava-shared-resources/
Author: CCAI group
Maintainer: Luke Dorney
Maintainer-email: luke.dorney@wolterskluwer.com
Requires-Python: >=3.10,<3.11
Classifier: Programming Language :: Python :: 3
Classifier: Programming Language :: Python :: 3.10
Requires-Dist: beautifulsoup4 (>=4.11.2,<5.0.0)
Requires-Dist: boto3 (>=1.26.78,<2.0.0)
Requires-Dist: fastapi (==0.109.2)
Requires-Dist: ftfy (>=6.1.1,<7.0.0)
Requires-Dist: gunicorn (==22.0.0)
Requires-Dist: json-logging-py (>=0.2,<0.3)
Requires-Dist: lxml (>=4.9.2,<5.0.0)
Requires-Dist: numpy (>=1.23.5,<2.0.0)
Requires-Dist: openpyxl (>=3.1.2,<4.0.0)
Requires-Dist: pandas (>=2.0.0,<3.0.0)
Requires-Dist: pydantic (>=2.5.0,<3.0.0)
Requires-Dist: pydantic-settings (>=2.3.4,<3.0.0)
Requires-Dist: requests (==2.32.2)
Requires-Dist: setuptools (>=70.0.0,<71.0.0)
Requires-Dist: tomli (==2.0.1)
Requires-Dist: tomlkit (>=0.12.1,<0.13.0)
Project-URL: Repository, https://bitbucket.wolterskluwer.io/projects/CCAI/repos/ava-shared-resources/
